bioprocessnexus/__init__.py
bioprocessnexus/data_managment.py
bioprocessnexus/explanations.py
bioprocessnexus/helpers.py
bioprocessnexus/hist.py
bioprocessnexus/interact_hist.py
bioprocessnexus/main.py
bioprocessnexus/mc_subsampling.py
bioprocessnexus/model_training.py
bioprocessnexus/optimizer.py
bioprocessnexus/performance_eval.py
bioprocessnexus/prediction_making.py
bioprocessnexus/scaling_performance.py
bioprocessnexus-1.0.5.dist-info/LICENSE
bioprocessnexus-1.0.5.dist-info/METADATA
bioprocessnexus-1.0.5.dist-info/WHEEL
bioprocessnexus-1.0.5.dist-info/top_level.txt
bioprocessnexus-1.0.5.dist-info/RECORD
