Metadata-Version: 2.1
Name: bioprocessnexus
Version: 1.0.5
Summary: README.md
Author-email: Matthias Medll <matthias.medl@chello.at>
License-File: LICENSE
Requires-Dist: requests
Requires-Dist: importlib-metadata ; python_version < "3.10"
